custom_models/MobileNetV2.py
custom_models/__init__.py
pkgs/Utilities.py
pkgs/__init__.py
pytorch_vision_utils/CustomModels.py
pytorch_vision_utils/Utilities.py
pytorch_vision_utils/__init__.py
pytorch_vision_utils/preprocessing.py
pytorch_vision_utils/train.py
pytorch_vision_utils-0.3.1.data/scripts/preprocessing.py
pytorch_vision_utils-0.3.1.data/scripts/train.py
pytorch_vision_utils-0.3.1.dist-info/LICENSE
pytorch_vision_utils-0.3.1.dist-info/METADATA
pytorch_vision_utils-0.3.1.dist-info/WHEEL
pytorch_vision_utils-0.3.1.dist-info/top_level.txt
pytorch_vision_utils-0.3.1.dist-info/RECORD
