Metadata-Version: 2.1
Name: pytorch-vision-utils
Version: 0.3.1
Summary: PyTorch training and data visualization utilities
Home-page: https://github.com/nclgbd/PyTorch-Utilities
Author: Nicole Gu
Author-email: nicoleguob@gmail.com
License: UNKNOWN
Platform: UNKNOWN
Classifier: Programming Language :: Python :: 3
Classifier: License :: OSI Approved :: MIT License
Classifier: Operating System :: OS Independent
Requires-Python: >=3.6
Requires-Dist: pretrainedmodels
